spaghetti/__init__.py
spaghetti/analysis.py
spaghetti/network.py
spaghetti/util.py
spaghetti/tests/__init__.py
spaghetti/tests/test_network.py
spaghetti-1.7.5.post1.dist-info/LICENSE.txt
spaghetti-1.7.5.post1.dist-info/METADATA
spaghetti-1.7.5.post1.dist-info/WHEEL
spaghetti-1.7.5.post1.dist-info/top_level.txt
spaghetti-1.7.5.post1.dist-info/RECORD
