Metadata-Version: 2.1
Name: spaghetti
Version: 1.7.5.post1
Summary: Analysis of Network-constrained Spatial Data
Maintainer-email: "James D. Gaboardi" <jgaboardi@gmail.com>
License: BSD 3-Clause
Project-URL: Home, https://pysal.org/spaghetti/
Project-URL: Repository, https://github.com/pysal/spaghetti
Keywords: spatial statistics,networks,graphs
Classifier: Programming Language :: Python :: 3
Classifier: License :: OSI Approved :: BSD License
Classifier: Operating System :: OS Independent
Classifier: Intended Audience :: Science/Research
Classifier: Topic :: Scientific/Engineering :: GIS
Requires-Python: >=3.10
License-File: LICENSE.txt
Requires-Dist: esda >=2.1
Requires-Dist: libpysal >=4.6
Requires-Dist: numpy >=1.22
Requires-Dist: pandas !=1.5.0,>=1.4
Requires-Dist: rtree >=1.0
Requires-Dist: scipy >=1.8
Provides-Extra: dev
Requires-Dist: ruff ; extra == 'dev'
Requires-Dist: pre-commit ; extra == 'dev'
Provides-Extra: docs
Requires-Dist: nbsphinx ; extra == 'docs'
Requires-Dist: numpydoc ; extra == 'docs'
Requires-Dist: sphinx ; extra == 'docs'
Requires-Dist: sphinxcontrib-bibtex ; extra == 'docs'
Requires-Dist: sphinx-bootstrap-theme ; extra == 'docs'
Provides-Extra: nb_conda
Requires-Dist: matplotlib ; extra == 'nb_conda'
Requires-Dist: matplotlib-scalebar ; extra == 'nb_conda'
Requires-Dist: pulp ; extra == 'nb_conda'
Requires-Dist: seaborn ; extra == 'nb_conda'
Requires-Dist: splot ; extra == 'nb_conda'
Requires-Dist: watermark ; extra == 'nb_conda'
Provides-Extra: nb_pypi
Requires-Dist: mip ; extra == 'nb_pypi'
Requires-Dist: ortools ; extra == 'nb_pypi'
Provides-Extra: plus
Requires-Dist: geopandas >=0.12 ; extra == 'plus'
Requires-Dist: shapely >=2.0 ; extra == 'plus'
Provides-Extra: tests
Requires-Dist: pytest ; extra == 'tests'
Requires-Dist: pytest-cov ; extra == 'tests'
Requires-Dist: pytest-timeout ; extra == 'tests'
Requires-Dist: pytest-xdist ; extra == 'tests'
Requires-Dist: codecov ; extra == 'tests'
Requires-Dist: coverage ; extra == 'tests'
Requires-Dist: twine ; extra == 'tests'
Requires-Dist: wheel ; extra == 'tests'
